basketball_reference_web_scraper/__init__.py
basketball_reference_web_scraper/client.py
basketball_reference_web_scraper/data.py
basketball_reference_web_scraper/errors.py
basketball_reference_web_scraper/html.py
basketball_reference_web_scraper/http_service.py
basketball_reference_web_scraper/output/__init__.py
basketball_reference_web_scraper/output/columns.py
basketball_reference_web_scraper/output/fields.py
basketball_reference_web_scraper/output/service.py
basketball_reference_web_scraper/output/writers.py
basketball_reference_web_scraper/parser_service.py
basketball_reference_web_scraper/parsers.py
basketball_reference_web_scraper/utilities.py
basketball_reference_web_scraper-4.15.4.dist-info/LICENSE
basketball_reference_web_scraper-4.15.4.dist-info/METADATA
basketball_reference_web_scraper-4.15.4.dist-info/WHEEL
basketball_reference_web_scraper-4.15.4.dist-info/RECORD
