Metadata-Version: 2.1
Name: basketball_reference_web_scraper
Version: 4.15.4
Summary: A Basketball Reference client that generates data by scraping the website
Home-page: https://jaebradley.github.io/basketball_reference_web_scraper
License: MIT
Keywords: NBA,Basketball,Basketball,Reference,basketball-reference.com
Author: Jae Bradley
Author-email: jae.b.bradley@gmail.com
Maintainer: Jae Bradley
Maintainer-email: jae.b.bradley@gmail.com
Requires-Python: >=3.7,<4.0
Classifier: License :: OSI Approved :: MIT License
Classifier: Operating System :: OS Independent
Classifier: Programming Language :: Python :: 3
Classifier: Programming Language :: Python :: 3.7
Classifier: Programming Language :: Python :: 3.8
Classifier: Programming Language :: Python :: 3.9
Classifier: Programming Language :: Python :: 3.10
Classifier: Programming Language :: Python :: 3.11
Requires-Dist: lxml (>=5.1.0,<6.0.0)
Requires-Dist: pytz (>=2024.1,<2025.0)
Requires-Dist: requests (>=2.31.0,<3.0.0)
Project-URL: Repository, https://github.com/jaebradley/basketball_reference_web_scraper
Project-URL: issues, https://github.com/jaebradley/basketball_reference_web_scraper/issues
Project-URL: pull_requests, https://github.com/jaebradley/basketball_reference_web_scraper/pull_requests
